mytestmodule456/__init__.py
mytestmodule456/add.py
mytestmodule456/sub.py
mytestmodule456/extras/__init__.py
mytestmodule456/extras/mult.py
mytestmodule456-0.0.8.dist-info/METADATA
mytestmodule456-0.0.8.dist-info/WHEEL
mytestmodule456-0.0.8.dist-info/top_level.txt
mytestmodule456-0.0.8.dist-info/RECORD
